<Properties StartupConfiguration="{2C8426CB-4EA4-49A8-AECE-0B196B5BE5EE}|Default">
  <MonoDevelop.Ide.Workbench ActiveDocument="TXM/Pages/Rounds.razor">
    <Files>
      <File FileName="TXM/Pages/Pairings.razor" Line="16" Column="74" />
      <File FileName="TXM.Core/TournamentController.cs" Line="252" Column="30" />
      <File FileName="TXM/Pages/Rounds.razor" Line="31" Column="1" />
      <File FileName="TXM/Pages/Index.razor" Line="1" Column="1" />
      <File FileName="TXM/Program.cs" Line="1" Column="1" />
      <File FileName="TXM/App.razor" Line="1" Column="1" />
      <File FileName="TXM/Shared/MainLayout.razor" Line="16" Column="43" />
      <File FileName="TXM/_Imports.razor" Line="11" Column="16" />
      <File FileName="TXM.Core/Tournament.cs" Line="708" Column="25" />
      <File FileName="TXM.Core/Rules/XWing25Rules.cs" Line="94" Column="1" />
    </Files>
    <Pads>
      <Pad Id="ProjectPad">
        <State name="__root__">
          <Node name="TXM" expanded="True">
            <Node name="TXM" expanded="True">
              <Node name="Pages" expanded="True" />
              <Node name="Shared" expanded="True" />
            </Node>
            <Node name="TXM.Core" expanded="True">
              <Node name="Rules" expanded="True" />
            </Node>
          </Node>
        </State>
      </Pad>
      <Pad Id="MonoDevelop.Debugger.WatchPad">
        <State />
      </Pad>
    </Pads>
  </MonoDevelop.Ide.Workbench>
  <MonoDevelop.Ide.DebuggingService.PinnedWatches />
  <MonoDevelop.Ide.Workspace ActiveConfiguration="Debug" />
  <Xamarin.Addins.Core.Project ActiveDebugTarget="MyAppleMacCatalystID" />
  <MultiItemStartupConfigurations />
  <MonoDevelop.Ide.DebuggingService.Breakpoints>
    <BreakpointStore />
  </MonoDevelop.Ide.DebuggingService.Breakpoints>
  <MonoDevelop.Ide.ItemProperties.TXM PreferredExecutionTarget="/Applications/Safari.app" />
</Properties>